<?xml version="1.0" encoding="UTF-8" ?>
<interface name="FTTHProcess.InstallRemoveEquipmentSolveIssueInterface">
  <description><![CDATA[
    <p style="margin-top: 0">
      Interface respons&#225;vel por agrupar as opera&#231;&#245;es da atividade manual de
      Instalar/Retirar Equipamento - Pend&#234;ncia.
    </p>
  ]]></description>
  <guid>{52ccba3e-2522-4779-848c-c1a3e3fb9b50}</guid>
  <label>Install Remove Equipment Solve Issue Interface</label>
  <metaVersion>3</metaVersion>
  <operationList>
    <operation name="InstallRemoveEquipmentSolveIssueTask" type="oper">
      <label>Install Remove Equipment Solve Issue Task</label>
      <type>One-Way</type>
    </operation>
    <operation name="InstallRemoveEquipmentSolveIssueSuccess" type="oper">
      <label>Install Remove Equipment Solve Issue Success</label>
      <type>Notification</type>
    </operation>
  </operationList>
  <revision>2</revision>
</interface>