<?xml version="1.0" encoding="UTF-8" ?>
<dataStructure name="FTTHClickInterface.validateChangeAssociateResponse">
  <container>true</container>
  <guid>{a4c9ecb5-5931-4bce-b86d-291a36d94bc2}</guid>
  <label>validateChangeAssociateResponse</label>
  <metaVersion>4</metaVersion>
  <childList>
    <child name="sistema" type="dstruct">
      <datatype>true</datatype>
      <element>dtype_FTTHClickInterface.sistema</element>
      <guid>{750a2870-25f1-4d00-afe9-0336e30e1256}</guid>
      <label>sistema</label>
      <mandatory>true</mandatory>
    </child>
    <child name="codigo" type="dstruct">
      <datatype>true</datatype>
      <element>dtype_FTTHClickInterface.codigo</element>
      <guid>{9f93efc2-1b26-419e-9fbf-67eabf19d7ed}</guid>
      <label>codigo</label>
      <mandatory>true</mandatory>
    </child>
    <child name="descricao" type="dstruct">
      <datatype>true</datatype>
      <element>dtype_FTTHClickInterface.descricao</element>
      <guid>{f02ca94f-9fce-496b-b6a4-a7660bdb46d9}</guid>
      <label>descricao</label>
      <mandatory>true</mandatory>
    </child>
    <child name="appId" type="dstruct">
      <datatype>true</datatype>
      <element>dtype_FTTHClickInterface.appId</element>
      <guid>{ae509f00-9c21-4c15-a96e-480e5d1a912f}</guid>
      <label>appId</label>
      <mandatory>true</mandatory>
    </child>
    <child name="timeStamp" type="dstruct">
      <datatype>true</datatype>
      <element>dtype_FTTHClickInterface.timeStamp</element>
      <guid>{964ff9c8-330e-462d-9a43-6eedc5b98adf}</guid>
      <label>timeStamp</label>
      <mandatory>true</mandatory>
    </child>
    <child name="transactId" type="dstruct">
      <datatype>true</datatype>
      <element>dtype_FTTHClickInterface.transactId</element>
      <guid>{fd3ce9d1-e606-4976-ad61-0b1c253c2a01}</guid>
      <label>transactId</label>
      <mandatory>true</mandatory>
    </child>
    <child name="transactIdClick" type="dstruct">
      <datatype>true</datatype>
      <element>dtype_FTTHClickInterface.transactIdClick</element>
      <guid>{8ec8f335-2373-4a5e-af37-da5195292217}</guid>
      <label>transactIdClick</label>
      <mandatory>true</mandatory>
    </child>
    <child name="detalhes" type="dstruct">
      <datatype>true</datatype>
      <element>dtype_FTTHClickInterface.detalhes</element>
      <guid>{e66b034c-6bbe-403c-81da-2862c8c2ebea}</guid>
      <label>detalhes</label>
      <mandatory>true</mandatory>
    </child>
  </childList>
  <UserInterface name="UserInterface" type="tree">
    <defaultFolderImage>undefined</defaultFolderImage>
    <defaultLeafImage>undefined</defaultLeafImage>
    <element>dstruct_FTTHClickInterface.validateChangeAssociateResponse</element>
    <extends>tree_com.conceptwave.system.DataStructureUserInterface</extends>
    <tableDoc>doc_com.conceptwave.system.TreeDocument</tableDoc>
    <variableList>
      <variable name="model" type="uivar">
        <label>model</label>
        <valueType>dstruct_FTTHClickInterface.validateChangeAssociateResponse</valueType>
      </variable>
    </variableList>
    <vformList>
      <vform name="Forms" type="frmui">
        <extends>tree_com.conceptwave.system.DataStructureUserInterface/frmui_Forms</extends>
      </vform>
    </vformList>
  </UserInterface>
</dataStructure>