<?xml version="1.0" encoding="UTF-8" ?>
<dataStructure name="FTTHOrderManagementInterface.msgErroRequisicaoOM">
  <container>true</container>
  <guid>{079cee0e-c712-4b2b-aa0f-351a69a16c6e}</guid>
  <label>msgErroRequisicaoOM</label>
  <metaVersion>3</metaVersion>
  <childList>
    <child name="erro" type="dstruct">
      <datatype>true</datatype>
      <element>dtype_FTTHOrderManagementInterface.erroRequisicaoOM</element>
      <guid>{6933899f-28e7-401a-9fc4-ef95028bef3e}</guid>
      <label>erro</label>
    </child>
    <child name="numeroPedido" type="dstruct">
      <datatype>true</datatype>
      <element>dtype_FTTHCommon.numeroPedido</element>
      <guid>{8e4d62b2-f898-41cf-946a-b2e0e0e41313}</guid>
      <label>numeroPedido</label>
    </child>
    <child name="numeroOS" type="dstruct">
      <datatype>true</datatype>
      <element>dtype_FTTHCommon.numeroOS</element>
      <guid>{cb0ada7c-2f97-451d-a02d-0e683bf32a5d}</guid>
      <label>numeroOS</label>
    </child>
  </childList>
  <UserInterface name="UserInterface" type="tree">
    <defaultFolderImage>undefined</defaultFolderImage>
    <defaultLeafImage>undefined</defaultLeafImage>
    <element>dstruct_FTTHOrderManagementInterface.msgErroRequisicaoOM</element>
    <extends>tree_com.conceptwave.system.DataStructureUserInterface</extends>
    <tableDoc>doc_com.conceptwave.system.TreeDocument</tableDoc>
    <variableList>
      <variable name="model" type="uivar">
        <label>model</label>
        <valueType>dstruct_FTTHOrderManagementInterface.msgErroRequisicaoOM</valueType>
      </variable>
    </variableList>
    <vformList>
      <vform name="Forms" type="frmui">
        <extends>tree_com.conceptwave.system.DataStructureUserInterface/frmui_Forms</extends>
      </vform>
    </vformList>
  </UserInterface>
</dataStructure>